<?xml version="1.0" encoding="UTF-8"?>
<monster name="Lanturn" nameDescription="a Wild Lanturn" race="water" experience="500" speed="220" manacost="600">
  <health now="13500" max="13500"/>
  <look type="571" head="20" body="30" legs="40" feet="50" corpse="11430"/>
	<targetchange interval="5" chance="1000"/>
  <strategy attack="100" defense="0"/>


 
  <attacks>

    <attack name="melee" interval="2000" skill="19" attack="18"/>.
    <attack name="aqua tail" range="5" interval="2100" chance="18" min="-180" max="-245">
    </attack>
    <attack name="electric wave" range="5" interval="2600" chance="20" min="-100" max="-132">
    </attack>
    <attack name="water gun" range="5" interval="2400" chance="14" min="-150" max="-180">
    </attack>
    <attack name="super sonic" interval="7200" chance="50" range="5" target="1">
    </attack>
    <attack name="waterball" range="1" interval="2200" chance="17" min="-150" max="-190">
    </attack>
    <attack name="thunder" range="1" interval="2000" chance="15" min="-190" max="-240">
    </attack>

    <attack name="hydro cannon" range="1" interval="2000" chance="15" min="-290" max="-440">
    </attack>
    <attack name="water oath" interval="3000" chance="100" min="-400" max="-650">
   </attack>
  <attack name="thunder oath" interval="3000" chance="100" min="-400" max="-650">
   </attack>
  </attacks>



  <voices interval="5000" chance="10">
    <voice sentence="Chinchou"/>
    <voice sentence="Chinnn!" yell="1"/>
  </voices>

	<loot>
	<item id="6528" countmax="41" chance="100000"/> -- water gem
	<item id="8820" countmax="1" chance="27000"/> -- water pendant
	<item id="2277" countmax="1" chance="1000"/> -- water stone
	<item id="11788" countmax="1" chance="500"/>---- pacotinhos
	</loot>
<script>
<event name="Exp"/>
</script>


</monster>
